Metadata-Version: 2.1
Name: lyyddmsg
Version: 1.2
Summary: userfull application for  lyy
Author: lyy
Author-email: 
License: MIT
License-File: LICENSE
